cs_generator/CSGenerator.py
cs_generator/__init__.py
cs_generator/_constants.py
cs_generator/templates.py
cs_generator/utils.py
cs_generator-1.0.6.dist-info/METADATA
cs_generator-1.0.6.dist-info/WHEEL
cs_generator-1.0.6.dist-info/top_level.txt
cs_generator-1.0.6.dist-info/RECORD
